octopusv/__init__.py
octopusv/__main__.py
octopusv/bencher/__init__.py
octopusv/bencher/bench_utils.py
octopusv/bencher/sv_bencher.py
octopusv/cli/__init__.py
octopusv/cli/bench.py
octopusv/cli/cli.py
octopusv/cli/convert.py
octopusv/cli/merge.py
octopusv/cli/plot.py
octopusv/cli/somatic.py
octopusv/cli/stat.py
octopusv/cli/svcf2bed.py
octopusv/cli/svcf2bedpe.py
octopusv/cli/svcf2vcf.py
octopusv/converter/__init__.py
octopusv/converter/base.py
octopusv/converter/bnd2del.py
octopusv/converter/bnd2dup_pair.py
octopusv/converter/bnd2inv_pair.py
octopusv/converter/bnd_keeping.py
octopusv/converter/mpi2tra.py
octopusv/converter/mpm2tra.py
octopusv/converter/mprtra2tra.py
octopusv/converter/nobnd.py
octopusv/converter/snmd_dndpi2tra.py
octopusv/converter/snmd_dndpr_tra2tra.py
octopusv/converter/stra2tra.py
octopusv/filter/__init__.py
octopusv/filter/quality_filter.py
octopusv/formatter/svcf_to_bed_converter.py
octopusv/formatter/svcf_to_bedpe_converter.py
octopusv/formatter/svcf_to_vcf_converter.py
octopusv/merger/TRA_merge_logic.py
octopusv/merger/__init__.py
octopusv/merger/bnd_merge_logic.py
octopusv/merger/bnd_merger.py
octopusv/merger/multi_sample_writer.py
octopusv/merger/name_mapper.py
octopusv/merger/sv_merge_logic.py
octopusv/merger/sv_merger.py
octopusv/merger/sv_selector.py
octopusv/merger/tra_merger.py
octopusv/merger/upset_plotter.py
octopusv/ploter/__init__.py
octopusv/ploter/chromosome_plotter.py
octopusv/ploter/size_plotter.py
octopusv/ploter/type_plotter.py
octopusv/py.typed
octopusv/report/generator.py
octopusv/report/image2base.py
octopusv/report/logo.png
octopusv/report/template.html
octopusv/stater/__init__.py
octopusv/stater/chromosome_analyzer.py
octopusv/stater/genotype_analyzer.py
octopusv/stater/qc_analyzer.py
octopusv/stater/size_analyzer.py
octopusv/stater/sv_stater.py
octopusv/stater/type_analyzer.py
octopusv/sv.py
octopusv/transformer/__init__.py
octopusv/transformer/base.py
octopusv/transformer/mp_bnd.py
octopusv/transformer/no_bnd.py
octopusv-0.2.3.dist-info/LICENSE
octopusv-0.2.3.dist-info/METADATA
octopusv-0.2.3.dist-info/WHEEL
octopusv-0.2.3.dist-info/entry_points.txt
octopusv-0.2.3.dist-info/RECORD
