Metadata-Version: 2.1
Name: OctopuSV
Version: 0.2.3
Summary: OctopuSV: Advanced Structural Variant Analysis Toolkit
License: MIT
Author: Qingxiang Guo
Author-email: qingxiang.guo@northwestern.edu
Requires-Python: >=3.10,<4.0
Classifier: License :: OSI Approved :: MIT License
Classifier: Programming Language :: Python :: 3
Classifier: Programming Language :: Python :: 3.10
Classifier: Programming Language :: Python :: 3.11
Classifier: Programming Language :: Python :: 3.12
Requires-Dist: click (>=8.0,<8.1)
Requires-Dist: jinja2 (>=3.1.5,<4.0.0)
Requires-Dist: loguru (>=0.7.2,<0.8.0)
Requires-Dist: matplotlib (>=3.9.2,<4.0.0)
Requires-Dist: natsort (>=8.4.0,<9.0.0)
Requires-Dist: pytest-cov (>=4.1.0,<5.0.0)
Requires-Dist: rich (>=13.7.1,<14.0.0)
Requires-Dist: seaborn (>=0.13.2,<0.14.0)
Requires-Dist: typer (>=0.12.3,<0.13.0)
